grading_notes/__about__.py
grading_notes/__init__.py
grading_notes/main.py
grading_notes-0.0.1.dist-info/METADATA
grading_notes-0.0.1.dist-info/WHEEL
grading_notes-0.0.1.dist-info/RECORD
