Metadata-Version: 2.3
Name: grading-notes
Version: 0.0.1
Summary: Guide LLM to judge an answer better using grading notes.
Project-URL: Documentation, https://github.com/shabie/grading-notes#readme
Project-URL: Issues, https://github.com/shabie/grading-notes/issues
Project-URL: Source, https://github.com/shabie/grading-notes
Author-email: Shabie Iqbal <shabieiqbal@gmail.com>
License-Expression: Apache-2.0
Classifier: Development Status :: 4 - Beta
Classifier: Programming Language :: Python
Classifier: Programming Language :: Python :: 3.8
Classifier: Programming Language :: Python :: 3.9
Classifier: Programming Language :: Python :: 3.10
Classifier: Programming Language :: Python :: 3.11
Classifier: Programming Language :: Python :: 3.12
Classifier: Programming Language :: Python :: Implementation :: CPython
Classifier: Programming Language :: Python :: Implementation :: PyPy
Requires-Python: >=3.8
Requires-Dist: anthropic
Requires-Dist: instructor
Requires-Dist: langchain
Requires-Dist: langchain-anthropic
Requires-Dist: langchain-community
Requires-Dist: openai
Requires-Dist: python-dotenv
